pepkit/__init__.py
pepkit/cli.py
pepkit/utils.py
pepkit/version.py
pepkit/chem/__init__.py
pepkit/chem/constants.py
pepkit/chem/rmsd.py
pepkit/chem/standardize.py
pepkit/chem/cluster/__init__.py
pepkit/chem/cluster/clustering.py
pepkit/chem/conversion/__init__.py
pepkit/chem/conversion/conversion.py
pepkit/chem/conversion/cyclic.py
pepkit/chem/conversion/monomer_lib.py
pepkit/chem/conversion/monomer_templates.py
pepkit/chem/conversion/peptide_decoder.py
pepkit/chem/conversion/peptide_lib.py
pepkit/chem/conversion/utils.py
pepkit/chem/desc/__init__.py
pepkit/chem/desc/_property.py
pepkit/chem/desc/descriptor.py
pepkit/chem/desc/pepwl.py
pepkit/chem/desc/sequence.py
pepkit/examples/__init__.py
pepkit/examples/data.py
pepkit/examples/rosetta_data.py
pepkit/examples/rosetta_test/complex_1.pdb
pepkit/examples/rosetta_test/complex_2.pdb
pepkit/examples/rosetta_test/prepack/complex_1/complex_1_0001.pdb
pepkit/examples/rosetta_test/prepack/complex_1/prepack.sc
pepkit/examples/rosetta_test/prepack/complex_2/complex_2_0001.pdb
pepkit/examples/rosetta_test/prepack/complex_2/prepack.sc
pepkit/examples/rosetta_test/refinement/complex_1/complex_1_0001_0001.pdb
pepkit/examples/rosetta_test/refinement/complex_1/docking_scores.sc
pepkit/examples/rosetta_test/refinement/complex_2/complex_2_0001_0001.pdb
pepkit/examples/rosetta_test/refinement/complex_2/docking_scores.sc
pepkit/gen/__init__.py
pepkit/gen/assembler.py
pepkit/gen/dsl.py
pepkit/gen/enumeration.py
pepkit/gen/filters.py
pepkit/gen/io.py
pepkit/gen/samplers.py
pepkit/gen/utils.py
pepkit/graph/__init__.py
pepkit/graph/mol_to_graph.py
pepkit/graph/smiles_to_graph.py
pepkit/graph/utils.py
pepkit/graph/align/__init__.py
pepkit/graph/feature/__init__.py
pepkit/graph/feature/feature_space.py
pepkit/graph/vg/__init__.py
pepkit/graph/vg/parser.py
pepkit/graph/vg/vg.py
pepkit/graph/vg/vis.py
pepkit/io/__init__.py
pepkit/io/files.py
pepkit/io/fs.py
pepkit/io/logging.py
pepkit/io/paths.py
pepkit/metrics/__init__.py
pepkit-0.0.5.dist-info/METADATA
pepkit-0.0.5.dist-info/WHEEL
pepkit-0.0.5.dist-info/entry_points.txt
pepkit-0.0.5.dist-info/licenses/LICENSE
pepkit-0.0.5.dist-info/RECORD
