Metadata-Version: 2.4
Name: pepkit
Version: 0.0.5
Summary: A modular Python toolkit for peptide modelling, rescoring, and structural bioinformatics
Project-URL: Homepage, https://github.com/Vivi-tran/PepKit
Project-URL: Source, https://github.com/Vivi-tran/PepKit
Project-URL: Issues, https://github.com/Vivi-tran/PepKit/issues
Project-URL: Documentation, https://vivi-tran.github.io/PepKit/
Author-email: Ngoc-Vi Nguyen Tran <vi.tran@sund.ku.dk>
License: MIT
License-File: LICENSE
Classifier: Development Status :: 3 - Alpha
Classifier: Intended Audience :: Science/Research
Classifier: License :: OSI Approved :: MIT License
Classifier: Operating System :: OS Independent
Classifier: Programming Language :: Python :: 3
Classifier: Programming Language :: Python :: 3.11
Classifier: Topic :: Scientific/Engineering :: Bio-Informatics
Requires-Python: >=3.11
Requires-Dist: dockq>=2.1.3
Requires-Dist: joblib>=1.4.2
Requires-Dist: pandas>=2.2.0
Requires-Dist: rcsb-api>=1.5.0
Requires-Dist: seaborn>=0.13.2
Provides-Extra: all
Requires-Dist: mdanalysis>=2.9.0; extra == 'all'
Requires-Dist: openbabel-wheel>=3.1.1.21; extra == 'all'
Requires-Dist: peptides>=0.3.4; extra == 'all'
Requires-Dist: prolif>=2.0.3; extra == 'all'
Requires-Dist: rdkit>=2025.3.2; extra == 'all'
Requires-Dist: scikit-learn>=1.4.0; extra == 'all'
Requires-Dist: umap-learn>=0.1.1; extra == 'all'
Provides-Extra: docs
Requires-Dist: myst-parser>=2.0; extra == 'docs'
Requires-Dist: sphinx-copybutton; extra == 'docs'
Requires-Dist: sphinx-design>=0.5; extra == 'docs'
Requires-Dist: sphinx-rtd-theme; extra == 'docs'
Requires-Dist: sphinx>=6.0; extra == 'docs'
Requires-Dist: sphinxcontrib-bibtex; extra == 'docs'
Provides-Extra: modelling
Requires-Dist: mdanalysis>=2.9.0; extra == 'modelling'
Requires-Dist: openbabel-wheel>=3.1.1.21; extra == 'modelling'
Requires-Dist: peptides>=0.3.4; extra == 'modelling'
Requires-Dist: prolif>=2.0.3; extra == 'modelling'
Requires-Dist: rdkit>=2025.3.2; extra == 'modelling'
